{"name":"extract-paired-reads.py","description":"Take a mixture of reads and split into pairs and orphans.","options":[{"names":["--version"],"argument":"","description":"show program's version number and exit"},{"names":["--info"],"argument":"","description":"print citation information"},{"names":["-h","--help"],"argument":"","description":"show this help message and exit"},{"names":["-d","--output-dir"],"argument":"OUTPUT_DIR","description":"Output split reads to specified directory. Creates directory if necessary (default: )"},{"names":["-p","--output-paired"],"argument":"filename","description":"Output paired reads to this file (default: None)"},{"names":["-s","--output-single"],"argument":"filename","description":"Output orphaned reads to this file (default: None)"},{"names":["-f","--force"],"argument":"","description":"Overwrite output file if it exists (default: False)"},{"names":["--gzip"],"argument":"","description":"Compress output using gzip (default: False)"},{"names":["--bzip"],"argument":"","description":"Compress output using bzip2 (default: False)"}],"version":"khmer 2.1.1"}
