{"name":"lftp","description":"Sophisticated file transfer program","usage":"lftp [-d] [-e cmd] [-p port] [-u user[,pass]] [site]\nlftp -f script_file\nlftp -c commands\nlftp --version\nlftp --help","options":[{"names":["-f"],"argument":"<file>","description":"execute commands from the file and exit"},{"names":["-c"],"argument":"<cmd>","description":"execute the commands and exit"},{"names":["--norc"],"argument":"","description":"don't execute rc files from the home directory"},{"names":["--help"],"argument":"","description":"print this help and exit"},{"names":["--version"],"argument":"","description":"print lftp version and exit"},{"names":["-e"],"argument":"<cmd>","description":"execute the command just after selecting"},{"names":["-u"],"argument":"<user>[,<pass>]","description":"use the user/password for authentication"},{"names":["-p"],"argument":"<port>","description":"use the port for connection"},{"names":["-s"],"argument":"<slot>","description":"assign the connection to this slot"},{"names":["-d"],"argument":"","description":"switch on debugging mode"}],"version":"4.9.2","tldr":"> Sophisticated file transfer program.\n> More information: <https://lftp.yar.ru/lftp-man.html>.\n\n- Connect to an FTP server:\n\n`lftp {{ftp.example.com}}`\n\n- Download multiple files (glob expression):\n\n`mget {{path/to/*.png}}`\n\n- Upload multiple files (glob expression):\n\n`mput {{path/to/*.zip}}`\n\n- Delete multiple files on the remote server:\n\n`mrm {{path/to/*.txt}}`\n\n- Rename a file on the remote server:\n\n`mv {{original_filename}} {{new_filename}}`\n\n- Download or update an entire directory:\n\n`mirror {{path/to/remote_dir}} {{path/to/local_output_dir}}`\n\n- Upload or update an entire directory:\n\n`mirror -R {{path/to/local_dir}} {{path/to/remote_output_dir}}`\n"}
